.coveragerc
.pylintrc
.testr.conf
AUTHORS
ChangeLog
HACKING.rst
LICENSE
MANIFEST.in
README.rst
openstack-common.conf
requirements.txt
setup.cfg
setup.py
test-requirements.txt
tox.ini
doc/source/conf.py
doc/source/index.rst
magnetodbclient/__init__.py
magnetodbclient/client.py
magnetodbclient/shell.py
magnetodbclient/streaming_shell.py
magnetodbclient/version.py
magnetodbclient/common/__init__.py
magnetodbclient/common/clientmanager.py
magnetodbclient/common/command.py
magnetodbclient/common/exceptions.py
magnetodbclient/common/serializer.py
magnetodbclient/common/utils.py
magnetodbclient/common/validators.py
magnetodbclient/magnetodb/__init__.py
magnetodbclient/magnetodb/client.py
magnetodbclient/magnetodb/v1/__init__.py
magnetodbclient/magnetodb/v1/item.py
magnetodbclient/magnetodb/v1/table.py
magnetodbclient/openstack/__init__.py
magnetodbclient/openstack/common/__init__.py
magnetodbclient/openstack/common/gettextutils.py
magnetodbclient/openstack/common/importutils.py
magnetodbclient/openstack/common/jsonutils.py
magnetodbclient/openstack/common/strutils.py
magnetodbclient/openstack/common/timeutils.py
magnetodbclient/tests/__init__.py
magnetodbclient/tests/test_auth.py
magnetodbclient/tests/test_shell.py
magnetodbclient/v1/__init__.py
magnetodbclient/v1/client.py
magnetodbclient/v1/client_base.py
magnetodbclient/v1/streaming_client.py
python_magnetodbclient.egg-info/PKG-INFO
python_magnetodbclient.egg-info/SOURCES.txt
python_magnetodbclient.egg-info/dependency_links.txt
python_magnetodbclient.egg-info/entry_points.txt
python_magnetodbclient.egg-info/not-zip-safe
python_magnetodbclient.egg-info/pbr.json
python_magnetodbclient.egg-info/requires.txt
python_magnetodbclient.egg-info/top_level.txt
tools/magnetodb.bash_completion